QuantumLaboratory/__init__.py
QuantumLaboratory/core.py
QuantumLaboratory-1.0.1.dist-info/LICENSE
QuantumLaboratory-1.0.1.dist-info/METADATA
QuantumLaboratory-1.0.1.dist-info/WHEEL
QuantumLaboratory-1.0.1.dist-info/top_level.txt
QuantumLaboratory-1.0.1.dist-info/RECORD
