Metadata-Version: 2.1
Name: QuantumLaboratory
Version: 1.0.1
Summary: A Python library for quantum tests.
Author: Mohammad Taha Gorji
Author-email: MohammadTahaGorjiProfile@gmail.com
Classifier: Programming Language :: Python :: 3
Classifier: License :: OSI Approved :: MIT License
Classifier: Operating System :: OS Independent
Requires-Python: >=3.6
License-File: LICENSE
Requires-Dist: pyVmomi
Requires-Dist: pyautogui
Requires-Dist: psutil
